base58check/__init__.py
base58check-1.0.2.dist-info/LICENSE.txt
base58check-1.0.2.dist-info/METADATA
base58check-1.0.2.dist-info/RECORD
base58check-1.0.2.dist-info/WHEEL
base58check-1.0.2.dist-info/top_level.txt
tests/__init__.py
tests/test_base58check.py
