Metadata-Version: 1.2
Name: base58check
Version: 1.0.2
Summary: Base58check encoding and decoding of binary data
Home-page: https://github.com/joeblackwaslike/base58check
Author: Joe Black
Author-email: me@joeblack.nyc
Maintainer: Joe Black
Maintainer-email: me@joeblack.nyc
License: MIT
Download-URL: https://github.com/joeblackwaslike/base58check/tarball/v1.0.2
Keywords: base58,base58check,encoding,decoding,bitcoin,altcoin
Platform: UNKNOWN
Classifier: Development Status :: 4 - Beta
Classifier: Intended Audience :: Developers
Classifier: Operating System :: OS Independent
Classifier: Natural Language :: English
Classifier: License :: OSI Approved :: MIT License
Classifier: Programming Language :: Python :: 3
Classifier: Programming Language :: Python :: 3.3
Classifier: Programming Language :: Python :: 3.4
Classifier: Programming Language :: Python :: 3.5
Classifier: Programming Language :: Python :: 3.6
Classifier: Programming Language :: Python :: 3 :: Only
Classifier: Topic :: Internet :: WWW/HTTP
Classifier: Topic :: Software Development
Classifier: Topic :: Security :: Cryptography
Classifier: Topic :: Text Processing
Classifier: Topic :: Utilities
Classifier: Topic :: Software Development :: Libraries :: Python Modules
